tmod-0.1.0.dist-info/DESCRIPTION.rst
tmod-0.1.0.dist-info/METADATA
tmod-0.1.0.dist-info/RECORD
tmod-0.1.0.dist-info/WHEEL
tmod-0.1.0.dist-info/entry_points.txt
tmod-0.1.0.dist-info/metadata.json
tmod-0.1.0.dist-info/top_level.txt
tmod_tools/__init__.py
tmod_tools/__main__.py
tmod_tools/cli.py
